win_depends/__init__.py
win_depends/cli.py
win_depends/core.py
win_depends/edge.py
win_depends/graph.py
win_depends/node.py
win_depends/printer.py
win_depends-0.1.5.2.dist-info/METADATA
win_depends-0.1.5.2.dist-info/WHEEL
win_depends-0.1.5.2.dist-info/entry_points.txt
win_depends-0.1.5.2.dist-info/top_level.txt
win_depends-0.1.5.2.dist-info/RECORD
