Metadata-Version: 2.4
Name: win_depends
Version: 0.1.5.2
Summary: Windows DLL/EXE dependency tree and graph tool
Author: Vorga
License: MIT
Requires-Python: >=3.6
Requires-Dist: tqdm>=4.64.1
Requires-Dist: pefile>=2024.5.17
Dynamic: author
Dynamic: license
Dynamic: requires-dist
Dynamic: requires-python
Dynamic: summary
